LICENSE
README.md
setup.py
src/toqen/__init__.py
src/toqen/toqen.py
src/toqen.egg-info/PKG-INFO
src/toqen.egg-info/SOURCES.txt
src/toqen.egg-info/dependency_links.txt
src/toqen.egg-info/requires.txt
src/toqen.egg-info/top_level.txt