Metadata-Version: 2.1
Name: toqen
Version: 0.0.0.6
Summary: Toqen AI client distributed as a python package
Author: Niro
Author-email: niro@toqen.ai
License-File: LICENSE
Requires-Dist: requests
Requires-Dist: python-dotenv
